{
  "swagger": "2.0",
  "info": {
    "title": "auth/v1/auth_service.proto",
    "version": "version not set"
  },
  "tags": [
    {
      "name": "auth.v1.AuthService"
    }
  ],
  "consumes": [
    "application/json"
  ],
  "produces": [
    "application/json"
  ],
  "paths": {
    "/v1/auth/introspect": {
      "post": {
        "summary": "Introspect an access token",
        "description": "Checks whether an access token is still active and returns its claims (user ID, expiry).",
        "operationId": "AuthService_IntrospectToken",
        "responses": {
          "200": {
            "description": "A successful response.",
            "schema": {
              "$ref": "#/definitions/v1IntrospectTokenResponse"
            }
          },
          "default": {
            "description": "An unexpected error response.",
            "schema": {
              "$ref": "#/definitions/rpcStatus"
            }
          }
        },
        "parameters": [
          {
            "name": "body",
            "in": "body",
            "required": true,
            "schema": {
              "$ref": "#/definitions/v1IntrospectTokenRequest"
            }
          }
        ],
        "tags": [
          "Auth"
        ]
      }
    },
    "/v1/auth/login": {
      "post": {
        "summary": "Login with email/username and password",
        "description": "Authenticates the user and returns a pair of JWT tokens (access + refresh).",
        "operationId": "AuthService_Login",
        "responses": {
          "200": {
            "description": "A successful response.",
            "schema": {
              "$ref": "#/definitions/v1LoginResponse"
            }
          },
          "default": {
            "description": "An unexpected error response.",
            "schema": {
              "$ref": "#/definitions/rpcStatus"
            }
          }
        },
        "parameters": [
          {
            "name": "body",
            "in": "body",
            "required": true,
            "schema": {
              "$ref": "#/definitions/v1LoginRequest"
            }
          }
        ],
        "tags": [
          "Auth"
        ]
      }
    },
    "/v1/auth/logout": {
      "post": {
        "summary": "Logout",
        "description": "Invalidates the provided refresh token so it can no longer be used.",
        "operationId": "AuthService_Logout",
        "responses": {
          "200": {
            "description": "A successful response.",
            "schema": {
              "$ref": "#/definitions/v1LogoutResponse"
            }
          },
          "default": {
            "description": "An unexpected error response.",
            "schema": {
              "$ref": "#/definitions/rpcStatus"
            }
          }
        },
        "parameters": [
          {
            "name": "body",
            "in": "body",
            "required": true,
            "schema": {
              "$ref": "#/definitions/v1LogoutRequest"
            }
          }
        ],
        "tags": [
          "Auth"
        ]
      }
    },
    "/v1/auth/refresh": {
      "post": {
        "summary": "Refresh tokens",
        "description": "Exchanges a valid refresh token for a new access token and a rotated refresh token.",
        "operationId": "AuthService_Refresh",
        "responses": {
          "200": {
            "description": "A successful response.",
            "schema": {
              "$ref": "#/definitions/v1RefreshResponse"
            }
          },
          "default": {
            "description": "An unexpected error response.",
            "schema": {
              "$ref": "#/definitions/rpcStatus"
            }
          }
        },
        "parameters": [
          {
            "name": "body",
            "in": "body",
            "required": true,
            "schema": {
              "$ref": "#/definitions/v1RefreshRequest"
            }
          }
        ],
        "tags": [
          "Auth"
        ]
      }
    },
    "/v1/auth/register": {
      "post": {
        "summary": "Register a new user account",
        "description": "Creates a new user and returns a pair of JWT tokens (access + refresh).",
        "operationId": "AuthService_Register",
        "responses": {
          "200": {
            "description": "A successful response.",
            "schema": {
              "$ref": "#/definitions/v1RegisterResponse"
            }
          },
          "default": {
            "description": "An unexpected error response.",
            "schema": {
              "$ref": "#/definitions/rpcStatus"
            }
          }
        },
        "parameters": [
          {
            "name": "body",
            "in": "body",
            "required": true,
            "schema": {
              "$ref": "#/definitions/v1RegisterRequest"
            }
          }
        ],
        "tags": [
          "Auth"
        ]
      }
    }
  },
  "definitions": {
    "protobufAny": {
      "type": "object",
      "properties": {
        "@type": {
          "type": "string"
        }
      },
      "additionalProperties": {}
    },
    "rpcStatus": {
      "type": "object",
      "properties": {
        "code": {
          "type": "integer",
          "format": "int32"
        },
        "message": {
          "type": "string"
        },
        "details": {
          "type": "array",
          "items": {
            "type": "object",
            "$ref": "#/definitions/protobufAny"
          }
        }
      }
    },
    "v1IdempotencyKey": {
      "type": "object",
      "properties": {
        "key": {
          "type": "string"
        }
      }
    },
    "v1IntrospectTokenRequest": {
      "type": "object",
      "properties": {
        "accessToken": {
          "type": "string"
        }
      }
    },
    "v1IntrospectTokenResponse": {
      "type": "object",
      "properties": {
        "active": {
          "type": "boolean"
        },
        "userId": {
          "type": "string"
        },
        "expiresAt": {
          "type": "string",
          "format": "date-time"
        }
      }
    },
    "v1LoginRequest": {
      "type": "object",
      "properties": {
        "email": {
          "type": "string"
        },
        "username": {
          "type": "string"
        },
        "password": {
          "type": "string"
        }
      }
    },
    "v1LoginResponse": {
      "type": "object",
      "properties": {
        "accessToken": {
          "type": "string"
        },
        "refreshToken": {
          "type": "string"
        },
        "accessExpiresAt": {
          "type": "string",
          "format": "date-time"
        },
        "refreshExpiresAt": {
          "type": "string",
          "format": "date-time"
        }
      }
    },
    "v1LogoutRequest": {
      "type": "object",
      "properties": {
        "refreshToken": {
          "type": "string"
        }
      }
    },
    "v1LogoutResponse": {
      "type": "object"
    },
    "v1RefreshRequest": {
      "type": "object",
      "properties": {
        "refreshToken": {
          "type": "string"
        }
      }
    },
    "v1RefreshResponse": {
      "type": "object",
      "properties": {
        "accessToken": {
          "type": "string"
        },
        "refreshToken": {
          "type": "string"
        },
        "accessExpiresAt": {
          "type": "string",
          "format": "date-time"
        },
        "refreshExpiresAt": {
          "type": "string",
          "format": "date-time"
        }
      }
    },
    "v1RegisterRequest": {
      "type": "object",
      "properties": {
        "email": {
          "type": "string"
        },
        "password": {
          "type": "string"
        },
        "firstName": {
          "type": "string"
        },
        "lastName": {
          "type": "string"
        },
        "username": {
          "type": "string"
        },
        "timezone": {
          "type": "string"
        },
        "idempotencyKey": {
          "$ref": "#/definitions/v1IdempotencyKey"
        }
      }
    },
    "v1RegisterResponse": {
      "type": "object",
      "properties": {
        "accessToken": {
          "type": "string"
        },
        "refreshToken": {
          "type": "string"
        },
        "accessExpiresAt": {
          "type": "string",
          "format": "date-time"
        },
        "refreshExpiresAt": {
          "type": "string",
          "format": "date-time"
        }
      }
    }
  }
}
